odoo/addons/website_snippet_product_category/README.rst
odoo/addons/website_snippet_product_category/__init__.py
odoo/addons/website_snippet_product_category/__manifest__.py
odoo/addons/website_snippet_product_category/controllers/__init__.py
odoo/addons/website_snippet_product_category/controllers/website.py
odoo/addons/website_snippet_product_category/demo/demo.xml
odoo/addons/website_snippet_product_category/demo/pages.xml
odoo/addons/website_snippet_product_category/i18n/ca.po
odoo/addons/website_snippet_product_category/i18n/es.po
odoo/addons/website_snippet_product_category/i18n/fr.po
odoo/addons/website_snippet_product_category/i18n/it.po
odoo/addons/website_snippet_product_category/i18n/nl.po
odoo/addons/website_snippet_product_category/i18n/pt_BR.po
odoo/addons/website_snippet_product_category/i18n/website_snippet_product_category.pot
odoo/addons/website_snippet_product_category/models/__init__.py
odoo/addons/website_snippet_product_category/models/product_public_category.py
odoo/addons/website_snippet_product_category/readme/CONFIGURE.md
odoo/addons/website_snippet_product_category/readme/CONTRIBUTORS.md
odoo/addons/website_snippet_product_category/readme/CREDITS.md
odoo/addons/website_snippet_product_category/readme/DESCRIPTION.md
odoo/addons/website_snippet_product_category/readme/ROADMAP.md
odoo/addons/website_snippet_product_category/readme/USAGE.md
odoo/addons/website_snippet_product_category/static/description/icon.png
odoo/addons/website_snippet_product_category/static/description/index.html
odoo/addons/website_snippet_product_category/static/img/boxes_32.png
odoo/addons/website_snippet_product_category/static/src/img/s_product_category.png
odoo/addons/website_snippet_product_category/static/src/js/frontend.esm.js
odoo/addons/website_snippet_product_category/static/src/js/snippet.options.esm.js
odoo/addons/website_snippet_product_category/static/src/scss/snippet.scss
odoo_addon_website_snippet_product_category-18.0.1.0.0.5.dist-info/METADATA
odoo_addon_website_snippet_product_category-18.0.1.0.0.5.dist-info/WHEEL
odoo_addon_website_snippet_product_category-18.0.1.0.0.5.dist-info/top_level.txt
odoo_addon_website_snippet_product_category-18.0.1.0.0.5.dist-info/RECORD
